{
    "pdf_path": "input/Рац.предложение №1 (Герасимов).pdf",
    "pages": [
        {
            "page_number": 1,
            "text": "Вход. Ne\n\nРуководителю BM3\n(наименование подразделения\n\nTUL\n\nTHe впервые Oynet использовано предложение)\n\nNe | Фамилия, имя, Место работы, Обра- | Таб Вознаг- Подписи\n\nn/m | отчество рождения| занимаемая зова- № аждение | авторов о\nавтора должность (для ние азделить | распределении\n(соавтора) иногородних В %) авторского\n\nуказать место вознаграж-\nжительства)\n\n1 Герасимов | JIM MI, =,\nЮрий 1990 ведущий высшее | 181087 25 PES\nЛеонидович инженер-технолог | —\n\n2 Бобарикин ‚\nЮрий 1963 aout LY) высшее - 25 BY\njee aerate uo. П.О. Cyxoro “i\n\n3 Kom TIL,\n\nOner 1982 калибровщик высшее | 180342 25\nИванович (ведущий)\n\n4 Авдеев JIN WL,\n\nСергей 1983 начальник высшее | 180638\nВалентинович лаборатории\nЗАЯВЛЕНИЕ\n\nна рационализаторское предложение\n\nПрошу (просим) рассмотреть предложение под наименованием:\n«Методика расчета калибровки оправок косовалкового стана с грибовидными валками и\n\nприводными направляющими дисками Дишера»\n\n(краткое наименование рационализаторского предложения)\n\nпризнать его рационализаторским и принять к ИСЙОЛЬЗОВ&НИЮ.\n\nОПИСАНИЕ ПРЕДЛОЖЕНИЯ\n(писать разборчиво, без исправлений, отразить изменение конструкций изделия, технологии\nпроизводства HIM применяемой техники, изменение состава материала)\n\nВ настоящее время: расчет калибровки прошивных оправок и настройка прошивного стана в TIA\n20-168 ТПЦ _ОАО «БМЗ -— управляющая компания холдинга «БМК» производится на основании\n\nопыта технических специалистов ТПЦ и/или с применением системы проектирования «САВТА\nСРМ».\n\nНедостатки: отсутствует систематизированная методика расчета калибровки оправок прошивного\nстана ТПА 20-168 ТПЦ OAO «BM3 — управляющая компания холдинга «БМК». учитывающая\nискажение очага деформации при прошивке на повышенных углах подачи и циклическое\nфФормоизменение заготовки-гильзы 3a все время деформирования. Определение данных параметров в\nсистеме «CARTA CPM» производится на основании параметров конечного формоизменения\nзаготовки в гильзу. без учета цикличности процесса и последних экспериментальных исследований в\nданной области. Ha современном уровне развития ПЭВМ и численных методов. проведение опытных\nпрошивок при испытаниях оправок прошивного стана новых калибровок является нерациональным.\nтак как приводит к дополнительным издержкам.\n1",
            "status": "success"
        },
        {
            "page_number": 2,
            "text": "Предлагаю (ем):_расчет геометрических параметров оправок прошивного стана ТПА 20-168 ТПЦ\nпроизводить в соответствии с разработанной «Методикой расчета калибровки _ оправок\nкосовалкового стана с грибовидными валками и приводными направляющими дисками Дишера».\nДанная методика расчета имеет прикладную направленность и основана на передовом опыте\nпоперечно-винтовой прокатки (прошивки) трубных горячекатаных и непрерывнолитых заготовок,\nучете циклического формоизменения заготовки-гильзы по длине очага деформации стана, a также\nна применении современных _ численных _ методов (моделирование процесса прокатки с\nиспользованием метода конечно-элементного анализа).\n\nЭто позволит:_рассчитывать геометрические параметры (калибровку) оправок косовалкового\nпрошивного стана с грибовидными валками и приводными направляющими дисками Дишера (в\nчастности. в условиях ТПА 20-168 ТПЦ), производить оценку режимов прошивки с позиции\nдеформируемости трубных _ заготовок, избегая при этом _дорогостоящие и длительные\nэксперименты при освоении новых профилеразмеров гильз и испытании новых профилеразмеров\nоправок. Также данная методика расчета может использоваться в процессе обучения технических\nспециалистов ТПЦ. На основании _ данной _ методики _ можно _ создать _ уточненную\nавтоматизированную программу расчета калибровки прошивных оправок и режимов прошивки.\n\nДополнительные сведения © предложении: данная _ методика _ разработана в _ рамках\nдиссертационного исследования ведущего инженера-технолога [TM JIM ИЦ Герасимова Ю.Л.\nпод руководством завелующего кафедрой «Металлургия и литейное производство» УО «ГГТУ uM.\nП.О. Cyxoro», к.т.н.. доцента Бобарикина Ю.Л. на Temy «Оптимальная геометрия прошивных\nоправок__для трубопрокатного производства. обеспечивающая _высокие эксплуатационные\n\nхарактеристики и снижение затрат на производство прошивных оправок».\n(указать, куда и когда ранее подавалось автором (соавторами) такое предложение и решение, принятое по нему)\n\nЯ (мы) утверждаю (eM), что действительно являюсь (емся) автором (соавторами) данного\nпредложения. Мне (нам) известно, что в случае признания предложения секретным, я обязуюсь\n(емся) соблюдать правила секретности.\n\nПРИЛАГАЮТСЯ:\na) графические материалы (эскизы, чертежи, схемы, графики и т.д. на _ 47 листах\n6) технико-экономические расчеты, обоснование и т.п. на 0 листах\nв) прочие материалы на 0 листах.\nВсего на 47 листах.\n& 47 : Л72 20 fr. Автор (соавторы) inal 7, LLY Aefese uote, /\n( подписи)\n\nLOB. Le\nVz U.",
            "status": "success"
        },
        {
            "page_number": 3,
            "text": "ЗАКЛЮЧЕНИЕ ПО ПРЕДЛОЖЕНИЮ\n\nа) производственного подразделения (цеха, участка и т.п.)\nils URY Hes yolighol П QAO WIR OMA U KA __Kegborut\n\n(сущность тёхнического решения прелложенного автором)\n\nю‚‹’\\ь«‚‘ь.…ь лсс ум at ered on doy NAV Rees)\n\neTORMS. ¢ ynxtmou LWA ое SEE Manu Wu\n< — Т ~\n\n2\n\n(новизна в пределах завода)\n\n(полезность, целесообразность использования)\n\n\\А\\АШБ\\(!{Ъ\\)(М Ucpoiszoto ил 6.\nю……ъдд@к„\\ыи THY Lo in Geis Df « 12 » ot 2013-г.\n\n(должность) (подпись, дата)\n\n6) других подразделений (TY, OFM, ОГЭн, ОГЭл, УПиР и т.п.)\n\n1. / <Х м ст Cccce © ид и оее < /’‹с‘?б’л‹-й ч о« Се бдрен 4 е ek a ee\nЙ < Ss a\n\n(сущность технического решения предложенного автором) оя\n\nст ес сс сс „з ст #Г Cree OOF © CeO OOO pw сетсес е #\n\n< е aed нг\n\nBere еестенеб к ne rege 4 we iGense г OI I Cet ee pee fa ofhec He cape woe lec —\n\na\nсесесе © xane< She foe: PP? fei — ye аба от Ce Ee OF? орн\n(новизНа в пределах завода) 7\n\nfice Perr CK cece оп ве бФ ECP ENC owe eee 0› ayreoece « ее ее\nОЙЕ х SOS Se ear wee ae ee 7 < оаы — ee eee\nA\n3. Llhenecoce (fava e Ve Po ee ee Bs ed\nР (полезность, целесообразность gr a\n\net\n\n20 / .\n\nЛЕ СОЬ\n\n/ (сущность технического решения предложенного автором) _\n\n_1//‚’!“«'‹‘/’\"/‘ 4 (KMEY Cb MAME 20 G leg Po. (CG LE hd 490.3 be ata\nOY) His Les: sip ocrnty nie OC# Vie ciepy Seve, ufpciliea MOLY sige, xe \\ npciteub Lb\n2.4 (ё / ‹/«/ Atvelixfitty, - ЮЮ oil Letichite,\n¥. 7 { 7 7\nГ (новизна в пределах завода)\n\n(полезность, целесообразность использования)\n\n%‘//_*_______“_//_ — 0.\n\n(должность) (подпись, да';а)/ //\n\nЗаключение OOTHTH:",
            "status": "success"
        },
        {
            "page_number": 4,
            "text": "РЕШЕНИЯ НАЧАЛЬНИКА ЦЕХА (ГЛАВНОГО ИНЖЕНЕРА)\n\nПредложение принять к Предложение квалифицировать — Предложение отклоняется\n\nиспытанию рационализаторским и принять к — по причинам\nиспользованию\n\nИспытание предложения Использование предложения\n\nвозложить Ha TOB. возложить Ha TOB. Ko AQ 0 (0\n\nв срок до всрокдо _ \\Ч.07 {0\n\nНачальник цеха (Главный Начальник цеха (Главный Начальник цеха (Главный\nинженер) инженер) инженер)\n« » 20 о% » 20 г. « » 20 ° г.\n\nАКТ ОБ ИСПОЛЬЗОВАНИИ ПРЕДЛОЖЕНИЯ\nДанное предложение после проведенного испытания признано годным и с WIL\n20 /4r. использовано\n\nHa участке Yf, iM hi Wyre ich ЕГ РеОдО цеха\nв соответствии с описанием предложения )\nОтветственность за дальнейшее использование возлагается на TOB. @4 Л Xl.\n\nФамилии лиц, содействовавших внедрению предложения_ _ ——\n\nДанное предложение влияет на следующие показатели: GILLS u_tkaeeorto MADOC LTT ~\n‚ 4\nMA, 774\n\nПодписи\nНачальник (цеха\n\nУполномоченный по оапионализапии /’ WA a rd Ce tos 4 ZA -)\n\nОтветственный за эксплуатацию\n\nС началом использования предложения ознакомлен (ы)\n«_73 » OF 20/7г. _ — Автор (соавторы\n\nBE Л озн\nИЗМЕНЕНИЕ НОРМАТИВНОЙ И ТЕХНИЧЕСНОЙ ДОКУМЕНТАЦИИ\n\nНаименование документов Номер Дата изменения",
            "status": "success"
        }
    ],
    "languages": [
        "eng",
        "rus"
    ],
    "page_count": 4,
    "status": "success"
}